README.rst
setup.py
voidpp_tools/__init__.py
voidpp_tools/alchemy_encoder.py
voidpp_tools/cache.py
voidpp_tools/cli_utils.py
voidpp_tools/colors.py
voidpp_tools/compat.py
voidpp_tools/config_loader.py
voidpp_tools/daemon.py
voidpp_tools/dict_utils.py
voidpp_tools/http.py
voidpp_tools/job_delayer.py
voidpp_tools/json_config.py
voidpp_tools/json_encoder.py
voidpp_tools/logger_proxy.py
voidpp_tools/plugin_manager.py
voidpp_tools/terminal.py
voidpp_tools/timer.py
voidpp_tools.egg-info/PKG-INFO
voidpp_tools.egg-info/SOURCES.txt
voidpp_tools.egg-info/dependency_links.txt
voidpp_tools.egg-info/top_level.txt
voidpp_tools/mocks/__init__.py
voidpp_tools/mocks/file_system/__init__.py
voidpp_tools/mocks/file_system/handlers.py
voidpp_tools/mocks/file_system/utils.py