Metadata-Version: 1.0
Name: voidpp-tools
Version: 1.11.0
Summary: various python tools
Home-page: https://github.com/voidpp/python-tools.git
Author: Lajos Santa
Author-email: santa.lajos@coldline.hu
License: UNKNOWN
Platform: UNKNOWN
